{"version":1,"resource":"vscode-remote://wsl%2Bubuntu/home/gabrielardevol/code/gabrielardevol/fullstack-challenges/02-OOP/02-OO-Advanced/04-Instance-vs-Class/lib/restaurant.rb","entries":[{"id":"p5DG.rb","timestamp":1666092829310},{"id":"65kl.rb","timestamp":1666092849380},{"id":"GRew.rb","timestamp":1666092910550},{"id":"8Bwf.rb","timestamp":1666092988580},{"id":"VaOr.rb","source":"undoRedo.source","timestamp":1666092999660},{"id":"qcmG.rb","timestamp":1666093326220},{"id":"qAKQ.rb","timestamp":1666093338950},{"id":"3oZA.rb","timestamp":1666093367520},{"id":"AaMh.rb","timestamp":1666093383700},{"id":"2mbT.rb","timestamp":1666093452740},{"id":"CGUr.rb","timestamp":1666093476980},{"id":"RUa0.rb","timestamp":1666093494040},{"id":"FcSN.rb","timestamp":1666093539660},{"id":"US7l.rb","timestamp":1666093562970},{"id":"PQ6r.rb","timestamp":1666093589600},{"id":"rUVn.rb","timestamp":1666093665190},{"id":"kKVN.rb","timestamp":1666093730550},{"id":"OCj8.rb","timestamp":1666093822290},{"id":"b2LE.rb","timestamp":1666093851920},{"id":"XdAo.rb","timestamp":1666093890130},{"id":"hVHU.rb","timestamp":1666093900610},{"id":"LcLl.rb","timestamp":1666093920430},{"id":"S8Ci.rb","timestamp":1666093944520},{"id":"VP4I.rb","timestamp":1666093987490},{"id":"HcOM.rb","timestamp":1666093998250},{"id":"GvHu.rb","timestamp":1666094037740},{"id":"mECv.rb","timestamp":1666094067890},{"id":"DbkU.rb","timestamp":1666094102630},{"id":"W8tP.rb","timestamp":1666094128580},{"id":"KnZi.rb","timestamp":1666094167570},{"id":"pLsD.rb","timestamp":1666094199250},{"id":"2Q8S.rb","timestamp":1666094267000},{"id":"Zbqo.rb","timestamp":1666094312290},{"id":"FvmY.rb","timestamp":1666094359300},{"id":"Uzdb.rb","timestamp":1666094405670},{"id":"SX1U.rb","timestamp":1666094492630},{"id":"aivN.rb","timestamp":1666094513090},{"id":"Drjn.rb","timestamp":1666094559870},{"id":"bpAD.rb","timestamp":1666094594520},{"id":"RoPG.rb","timestamp":1666094607670},{"id":"n7oK.rb","timestamp":1666094623750},{"id":"Pnx2.rb","timestamp":1666094638500},{"id":"WuiA.rb","timestamp":1666094655990},{"id":"5jf4.rb","timestamp":1666094702630},{"id":"Lh0P.rb","timestamp":1666094723510},{"id":"y2Jm.rb","timestamp":1666094798120},{"id":"eGoI.rb","source":"undoRedo.source","timestamp":1666095067440},{"id":"2zQA.rb","timestamp":1666095171190},{"id":"ewXW.rb","timestamp":1666095254990},{"id":"vcKO.rb","timestamp":1666099508742}]}